page_counter/__init__.py
page_counter/cli.py
page_counter/dialects.py
page_counter/page_counter.py
page_counter-1.0.1.dist-info/LICENSE.txt
page_counter-1.0.1.dist-info/METADATA
page_counter-1.0.1.dist-info/RECORD
page_counter-1.0.1.dist-info/WHEEL
page_counter-1.0.1.dist-info/entry_points.txt
page_counter-1.0.1.dist-info/top_level.txt
