Metadata-Version: 2.1
Name: page-counter
Version: 1.0.1
Summary: Small Python library and commandline tool to count number of standard pages in the text, files and folders. Comes with common standard page dialects but is super easy to bring your own definition.
Home-page: https://github.com/bircow/page-counter
Author: Libor Jelinek
Author-email: ljelinek@virtage.com
License: MIT
Platform: UNKNOWN
Classifier: Development Status :: 5 - Production/Stable
Classifier: Intended Audience :: Developers
Classifier: Intended Audience :: End Users/Desktop
Classifier: License :: OSI Approved :: MIT License
Classifier: Topic :: Text Processing
Requires-Python: >=3
Requires-Dist: beautifulsoup4
